fairmeta/__init__.py
fairmeta/__main__.py
fairmeta/mappings.py
fairmeta/metadata_model.py
fairmeta/schema_definitions_hri.py
fairmeta/uploader_radboudfdp.py
fairmeta/gatherers/__init__.py
fairmeta/gatherers/gather_GC.py
fairmeta-0.0.4.dist-info/METADATA
fairmeta-0.0.4.dist-info/WHEEL
fairmeta-0.0.4.dist-info/entry_points.txt
fairmeta-0.0.4.dist-info/licenses/LICENSE
fairmeta-0.0.4.dist-info/RECORD
